{
  "$id": "root",
  "$schema": "http://json-schema.org/draft-07/schema#",
  "type": "object",
  "properties": {
    "url": {
      "type": "string",
      "default": "https://dev76384.service-now.com/",
      "examples": [
        "https://yourDevServiceNowInstanceCanonicalHostname/"
      ]
    },
    "auth": {
      "type": "object",
      "properties": {
        "username": {
          "type": "string",
          "default": "admin",
          "examples": [
            "devUsername"
          ]
        },
        "password": {
          "type": "string",
          "default": "Prisha1234!",
          "examples": [
            "devUserPassword"
          ]
        }
      },
      "required": [
        "username",
        "password"
      ],
      "additionalProperties": false
    },
    "serviceNowTable": {
      "type": "string",
      "default": "change_request",
      "examples": [
        "change_request"
      ]
    }
  },
  "required": [
    "url",
    "auth",
    "serviceNowTable"
  ],
  "additionalProperties": false
}